datapizza/embedders/fastembedder/__init__.py
datapizza/embedders/fastembedder/fastembedder.py
datapizza_ai_embedders_fastembedder-0.0.7.dist-info/METADATA
datapizza_ai_embedders_fastembedder-0.0.7.dist-info/WHEEL
datapizza_ai_embedders_fastembedder-0.0.7.dist-info/RECORD
